terminal_typing_test/__init__.py
terminal_typing_test/main.py
terminal_typing_test/monitor.py
terminal_typing_test/text/careers.txt
terminal_typing_test/text/constitution.txt
terminal_typing_test/text/short/careers-short.txt
terminal_typing_test/text/short/constitution-short.txt
terminal_typing_test/text/short/stocks-short.txt
terminal_typing_test/text/stocks.txt
terminal_typing_test/utils.py
terminal_typing_test-0.1.3.dist-info/entry_points.txt
terminal_typing_test-0.1.3.dist-info/WHEEL
terminal_typing_test-0.1.3.dist-info/METADATA
terminal_typing_test-0.1.3.dist-info/RECORD
